docuglean/__init__.py
docuglean/batch.py
docuglean/classify.py
docuglean/extract.py
docuglean/ocr.py
docuglean/types.py
docuglean/utils.py
docuglean/parsers/__init__.py
docuglean/parsers/csv.py
docuglean/parsers/docx.py
docuglean/parsers/pdf.py
docuglean/parsers/pptx.py
docuglean/parsers/spreadsheet.py
docuglean/providers/__init__.py
docuglean/providers/gemini.py
docuglean/providers/huggingface.py
docuglean/providers/local.py
docuglean/providers/mistral.py
docuglean/providers/openai.py
docuglean-1.1.0.dist-info/METADATA
docuglean-1.1.0.dist-info/WHEEL
docuglean-1.1.0.dist-info/licenses/LICENSE
docuglean-1.1.0.dist-info/RECORD
