Metadata-Version: 2.4
Name: docuglean
Version: 1.1.0
Summary: An SDK for intelligent document processing using SOTA VLLM models
Project-URL: Repository, https://github.com/docuglean-ai/docuglean-ocr
Project-URL: Issues, https://github.com/docuglean-ai/docuglean-ocr/issues
Author-email: Cernis Intelligence <dev@cernisintelligence.com>
License: Apache-2.0
License-File: LICENSE
Keywords: document,document-processing,llm,ocr,text-extraction
Requires-Python: >=3.11
Requires-Dist: beautifulsoup4>=4.12.0
Requires-Dist: google-genai>=1.32.0
Requires-Dist: httpx>=0.25.0
Requires-Dist: mammoth>=1.6.0
Requires-Dist: markdown>=3.6
Requires-Dist: mistralai>=0.0.10
Requires-Dist: openai>=1.0.0
Requires-Dist: openpyxl>=3.1.5
Requires-Dist: pdftext>=0.3.10
Requires-Dist: pydantic>=2.0.0
Requires-Dist: python-pptx>=0.6.23
Requires-Dist: transformers>=4.0.0
Provides-Extra: dev
Requires-Dist: pytest-asyncio>=0.24.0; extra == 'dev'
Requires-Dist: pytest>=8.0.0; extra == 'dev'
Requires-Dist: ruff>=0.12.0; extra == 'dev'
